litpose_app/__init__.py
litpose_app/config.py
litpose_app/config_default.yaml
litpose_app/config_default_multiview.yaml
litpose_app/datatypes.py
litpose_app/deps.py
litpose_app/main.py
litpose_app/ngdist/ng_app/3rdpartylicenses.txt
litpose_app/ngdist/ng_app/browser/app.component-XJ23PGQC.css.map
litpose_app/ngdist/ng_app/browser/create-model-dialog.component-XM4MKM6L.css.map
litpose_app/ngdist/ng_app/browser/error-dialog.component-HYLQSJEP.css.map
litpose_app/ngdist/ng_app/browser/extract-frames-dialog.component-DKKIPRKS.css.map
litpose_app/ngdist/ng_app/browser/favicon.ico
litpose_app/ngdist/ng_app/browser/index.html
litpose_app/ngdist/ng_app/browser/keypoint-container.component-AHUECMQE.css.map
litpose_app/ngdist/ng_app/browser/keypoint-container.component-QKLNXI3D.css.map
litpose_app/ngdist/ng_app/browser/labeler-page.component-W5BVHYFQ.css.map
litpose_app/ngdist/ng_app/browser/main-CJ6REFWX.js
litpose_app/ngdist/ng_app/browser/main-CJ6REFWX.js.map
litpose_app/ngdist/ng_app/browser/models-list.component-QX7QENIP.css.map
litpose_app/ngdist/ng_app/browser/models-page.component-P37C5RZI.css.map
litpose_app/ngdist/ng_app/browser/project-home-page.component-57TPLDT2.css.map
litpose_app/ngdist/ng_app/browser/project-settings.component-AD62BC7G.css.map
litpose_app/ngdist/ng_app/browser/project-settings.component-M7JLU4LS.css.map
litpose_app/ngdist/ng_app/browser/project_home_card_labeler.jpg
litpose_app/ngdist/ng_app/browser/project_home_card_models.png
litpose_app/ngdist/ng_app/browser/project_home_card_settings.jpg
litpose_app/ngdist/ng_app/browser/project_home_card_viewer.png
litpose_app/ngdist/ng_app/browser/static/favicon.ico
litpose_app/ngdist/ng_app/browser/static/project_home_card_labeler.jpg
litpose_app/ngdist/ng_app/browser/static/project_home_card_models.png
litpose_app/ngdist/ng_app/browser/static/project_home_card_settings.jpg
litpose_app/ngdist/ng_app/browser/static/project_home_card_viewer.png
litpose_app/ngdist/ng_app/browser/styles-U236RTUB.css
lightning_pose_app-2.0.5.0.dist-info/METADATA
lightning_pose_app-2.0.5.0.dist-info/WHEEL
lightning_pose_app-2.0.5.0.dist-info/RECORD
