Metadata-Version: 2.4
Name: lightning-pose-app
Version: 2.0.5.0
Summary: 
Requires-Python: >=3.10
Classifier: Programming Language :: Python :: 3
Classifier: Programming Language :: Python :: 3.10
Classifier: Programming Language :: Python :: 3.11
Classifier: Programming Language :: Python :: 3.12
Classifier: Programming Language :: Python :: 3.13
Classifier: Programming Language :: Python :: 3.14
Provides-Extra: dev
Requires-Dist: PyYAML (>=6.0.2,<6.1.0)
Requires-Dist: aiofiles (>=24.1.0,<24.2.0)
Requires-Dist: aniposelib (>=0.7.2,<0.8.0)
Requires-Dist: fastapi (>=0.116.0,<0.117.0)
Requires-Dist: honcho (>=2.0,<3.0)
Requires-Dist: httpx (>=0.28.0,<0.29.0) ; extra == "dev"
Requires-Dist: omegaconf (>=2.3.0,<2.4.0)
Requires-Dist: opencv-python (>=4.12.0.88,<4.13.0.0)
Requires-Dist: pandas (>=2.3.0,<2.4.0)
Requires-Dist: portalocker (>=3.2.0,<3.3.0)
Requires-Dist: psutil (>=7.0.0,<7.1.0)
Requires-Dist: pydantic-settings
Requires-Dist: pytest (>=8.4.0,<8.5.0) ; extra == "dev"
Requires-Dist: pytest-asyncio (>=1.0.0,<1.1.0) ; extra == "dev"
Requires-Dist: pytest-mock (>=3.14.0,<3.15.0) ; extra == "dev"
Requires-Dist: python-multipart
Requires-Dist: scikit-learn (>=1.7.1,<1.8.0)
Requires-Dist: tomli (>=2.2.0,<2.3.0)
Requires-Dist: tomli_w (>=1.2.0,<1.3.0)
Requires-Dist: tqdm (>=4.67.1,<4.68.0)
Requires-Dist: uvicorn[standard] (>=0.35.0,<0.36.0)
Requires-Dist: wcmatch (>=10.0,<11.0)
